{
	"last_link_id":212,
	"nodes":[
		{
			"outputs":[
				{
					"name":"CONDITIONING",
					"slot_index":0,
					"links":[
						56,
						185
					],
					"label":"CONDITIONING",
					"type":"CONDITIONING",
					"localized_name":"CONDITIONING"
				}
			],
			"color":"#322",
			"widgets_values":[
				""
			],
			"inputs":[
				{
					"name":"clip",
					"link":25,
					"label":"clip",
					"type":"CLIP",
					"localized_name":"clip"
				}
			],
			"flags":{
				"collapsed":true
			},
			"type":"CLIPTextEncode",
			"mode":0,
			"bgcolor":"#533",
			"size":[
				425.27801513671875,
				180.6060791015625
			],
			"pos":[
				-474.56292724609375,
				506.2453308105469
			],
			"id":7,
			"properties":{
				"cnr_id":"comfy-core",
				"ver":"0.3.27",
				"Node name for S&R":"CLIPTextEncode"
			},
			"order":12
		},
		{
			"outputs":[
				{
					"name":"IMAGE",
					"slot_index":0,
					"links":[
						139
					],
					"label":"IMAGE",
					"type":"IMAGE",
					"localized_name":"IMAGE"
				}
			],
			"color":"#432",
			"widgets_values":[
				"lanczos",
				0.5
			],
			"inputs":[
				{
					"name":"image",
					"link":122,
					"label":"image",
					"type":"IMAGE",
					"localized_name":"image"
				}
			],
			"flags":{
				"collapsed":true
			},
			"type":"ImageScaleBy",
			"mode":2,
			"bgcolor":"#653",
			"size":[
				226.8000030517578,
				83.74797058105469
			],
			"pos":[
				547.7832641601562,
				408.9073181152344
			],
			"id":102,
			"properties":{
				"cnr_id":"comfy-core",
				"ver":"0.3.27",
				"Node name for S&R":"ImageScaleBy"
			},
			"order":20
		},
		{
			"outputs":[
				{
					"name":"IMAGE",
					"slot_index":0,
					"links":[
						122
					],
					"label":"IMAGE",
					"type":"IMAGE",
					"localized_name":"IMAGE"
				}
			],
			"color":"#432",
			"widgets_values":[
				
			],
			"inputs":[
				{
					"name":"upscale_model",
					"link":121,
					"label":"upscale_model",
					"type":"UPSCALE_MODEL",
					"localized_name":"upscale_model"
				},
				{
					"name":"image",
					"link":199,
					"label":"image",
					"type":"IMAGE",
					"localized_name":"image"
				}
			],
			"flags":{
				"collapsed":true
			},
			"type":"ImageUpscaleWithModel",
			"mode":2,
			"bgcolor":"#653",
			"size":[
				226.8000030517578,
				46
			],
			"pos":[
				547.7832641601562,
				362.8274230957031
			],
			"id":100,
			"properties":{
				"cnr_id":"comfy-core",
				"ver":"0.3.27",
				"Node name for S&R":"ImageUpscaleWithModel"
			},
			"order":19
		},
		{
			"mode":2,
			"outputs":[
				{
					"name":"LATENT",
					"slot_index":0,
					"links":[
						197
					],
					"label":"LATENT",
					"type":"LATENT",
					"localized_name":"LATENT"
				}
			],
			"size":[
				140,
				46
			],
			"pos":[
				742.7877197265625,
				413.5119323730469
			],
			"widgets_values":[
				
			],
			"inputs":[
				{
					"name":"pixels",
					"link":139,
					"label":"pixels",
					"type":"IMAGE",
					"localized_name":"pixels"
				},
				{
					"name":"vae",
					"link":141,
					"label":"vae",
					"type":"VAE",
					"localized_name":"vae"
				}
			],
			"flags":{
				"collapsed":true
			},
			"id":110,
			"type":"VAEEncode",
			"properties":{
				"cnr_id":"comfy-core",
				"ver":"0.3.27",
				"Node name for S&R":"VAEEncode"
			},
			"order":21
		},
		{
			"outputs":[
				{
					"name":"UPSCALE_MODEL",
					"slot_index":0,
					"links":[
						121
					],
					"label":"UPSCALE_MODEL",
					"type":"UPSCALE_MODEL",
					"localized_name":"UPSCALE_MODEL"
				}
			],
			"color":"#432",
			"widgets_values":[
				"4x_NMKD-Siax_200k.pth"
			],
			"inputs":[
				
			],
			"flags":{
				"collapsed":true
			},
			"type":"UpscaleModelLoader",
			"mode":2,
			"bgcolor":"#653",
			"size":[
				301.6999206542969,
				58
			],
			"pos":[
				547.7832641601562,
				311.0662841796875
			],
			"id":101,
			"properties":{
				"cnr_id":"comfy-core",
				"ver":"0.3.27",
				"Node name for S&R":"UpscaleModelLoader"
			},
			"order":0
		},
		{
			"mode":0,
			"outputs":[
				{
					"name":"CLIP",
					"slot_index":0,
					"links":[
						24,
						25
					],
					"label":"CLIP",
					"type":"CLIP",
					"localized_name":"CLIP"
				}
			],
			"size":[
				351.0797119140625,
				106
			],
			"pos":[
				-893.8199462890625,
				412.67352294921875
			],
			"widgets_values":[
				"t5-v1_1-xxl-encoder-Q8_0.gguf",
				"clip_l.safetensors",
				"flux"
			],
			"inputs":[
				
			],
			"flags":{
				
			},
			"id":26,
			"type":"DualCLIPLoaderGGUF",
			"properties":{
				"cnr_id":"comfyui-gguf",
				"ver":"bc5223b0e37e053dbec2ea5e5f52c2fd4b8f712a",
				"Node name for S&R":"DualCLIPLoaderGGUF"
			},
			"order":1
		},
		{
			"mode":0,
			"outputs":[
				{
					"name":"CONDITIONING",
					"slot_index":0,
					"links":[
						55,
						184
					],
					"label":"CONDITIONING",
					"type":"CONDITIONING",
					"localized_name":"CONDITIONING"
				}
			],
			"size":[
				211.60000610351562,
				58
			],
			"pos":[
				-40.850181579589844,
				258.99200439453125
			],
			"widgets_values":[
				3.5
			],
			"inputs":[
				{
					"name":"conditioning",
					"link":11,
					"label":"conditioning",
					"type":"CONDITIONING",
					"localized_name":"conditioning"
				}
			],
			"flags":{
				
			},
			"id":11,
			"type":"FluxGuidance",
			"properties":{
				"cnr_id":"comfy-core",
				"ver":"0.3.27",
				"Node name for S&R":"FluxGuidance"
			},
			"order":14
		},
		{
			"mode":2,
			"outputs":[
				{
					"name":"IMAGE",
					"slot_index":0,
					"links":[
						210
					],
					"label":"IMAGE",
					"type":"IMAGE",
					"localized_name":"IMAGE"
				}
			],
			"size":[
				140,
				46
			],
			"pos":[
				816.828125,
				322.5050048828125
			],
			"widgets_values":[
				
			],
			"inputs":[
				{
					"name":"samples",
					"link":142,
					"label":"samples",
					"type":"LATENT",
					"localized_name":"samples"
				},
				{
					"name":"vae",
					"link":145,
					"label":"vae",
					"type":"VAE",
					"localized_name":"vae"
				}
			],
			"flags":{
				"collapsed":false
			},
			"id":111,
			"type":"VAEDecode",
			"properties":{
				"cnr_id":"comfy-core",
				"ver":"0.3.27",
				"Node name for S&R":"VAEDecode"
			},
			"order":23
		},
		{
			"mode":2,
			"outputs":[
				{
					"name":"IMAGE",
					"links":[
						211,
						212
					],
					"label":"IMAGE",
					"type":"IMAGE",
					"localized_name":"IMAGE"
				}
			],
			"size":[
				231.86183166503906,
				130
			],
			"pos":[
				982.43798828125,
				320.72216796875
			],
			"widgets_values":[
				"lanczos",
				2560,
				1440,
				"center"
			],
			"inputs":[
				{
					"name":"image",
					"link":210,
					"label":"image",
					"type":"IMAGE",
					"localized_name":"image"
				}
			],
			"flags":{
				
			},
			"id":184,
			"type":"ImageScale",
			"properties":{
				"cnr_id":"comfy-core",
				"ver":"0.3.39",
				"Node name for S&R":"ImageScale"
			},
			"order":24
		},
		{
			"mode":2,
			"outputs":[
				{
					"name":"output",
					"links":[
						
					],
					"label":"output",
					"type":"*",
					"localized_name":"output"
				}
			],
			"size":[
				160.06723022460938,
				26
			],
			"pos":[
				1248.1270751953125,
				325.4501953125
			],
			"widgets_values":[
				
			],
			"inputs":[
				{
					"name":"anything",
					"link":212,
					"label":"anything",
					"type":"*",
					"localized_name":"anything"
				}
			],
			"flags":{
				"collapsed":false
			},
			"id":144,
			"type":"easy cleanGpuUsed",
			"properties":{
				"cnr_id":"comfyui-easy-use",
				"ver":"9292f2286207928cfdade99ad1634103470c0799",
				"Node name for S&R":"easy cleanGpuUsed"
			},
			"order":26
		},
		{
			"mode":2,
			"outputs":[
				
			],
			"size":[
				822.1996459960938,
				537.2759399414062
			],
			"pos":[
				887.6319580078125,
				497.1765441894531
			],
			"widgets_values":[
				"2K",
				""
			],
			"inputs":[
				{
					"name":"images",
					"link":211,
					"label":"images",
					"type":"IMAGE",
					"localized_name":"images"
				}
			],
			"flags":{
				
			},
			"id":170,
			"type":"SaveImage",
			"title":"Save Image UPSCALED 2K",
			"properties":{
				"cnr_id":"comfy-core",
				"ver":"0.3.27",
				"Node name for S&R":"SaveImage"
			},
			"order":25
		},
		{
			"mode":0,
			"outputs":[
				{
					"name":"LATENT",
					"slot_index":0,
					"links":[
						187
					],
					"label":"LATENT",
					"type":"LATENT",
					"localized_name":"LATENT"
				}
			],
			"size":[
				315,
				262
			],
			"pos":[
				194.43919372558594,
				258.99200439453125
			],
			"widgets_values":[
				50,
				"fixed",
				30,
				1,
				"dpmpp_2m",
				"sgm_uniform",
				1
			],
			"inputs":[
				{
					"name":"model",
					"link":202,
					"label":"model",
					"type":"MODEL",
					"localized_name":"model"
				},
				{
					"name":"positive",
					"link":184,
					"label":"positive",
					"type":"CONDITIONING",
					"localized_name":"positive"
				},
				{
					"name":"negative",
					"link":185,
					"label":"negative",
					"type":"CONDITIONING",
					"localized_name":"negative"
				},
				{
					"name":"latent_image",
					"link":186,
					"label":"latent_image",
					"type":"LATENT",
					"localized_name":"latent_image"
				}
			],
			"flags":{
				
			},
			"id":163,
			"type":"KSampler",
			"properties":{
				"cnr_id":"comfy-core",
				"ver":"0.3.27",
				"Node name for S&R":"KSampler"
			},
			"order":15
		},
		{
			"outputs":[
				
			],
			"color":"#fff0",
			"inputs":[
				
			],
			"flags":{
				"allow_interaction":true
			},
			"type":"Label (rgthree)",
			"title":"!!! Change the seed manually",
			"mode":0,
			"bgcolor":"#fff0",
			"size":[
				260.166015625,
				20
			],
			"pos":[
				220.011962890625,
				197.8528289794922
			],
			"id":174,
			"properties":{
				"padding":0,
				"backgroundColor":"transparent",
				"fontFamily":"Arial",
				"borderRadius":0,
				"textAlign":"center",
				"fontSize":20,
				"fontColor":"#ffffff"
			},
			"order":2
		},
		{
			"mode":0,
			"outputs":[
				{
					"name":"IMAGE",
					"links":[
						198,
						201
					],
					"label":"IMAGE",
					"type":"IMAGE",
					"localized_name":"IMAGE"
				}
			],
			"size":[
				210,
				46
			],
			"pos":[
				544.4000854492188,
				206.806396484375
			],
			"widgets_values":[
				
			],
			"inputs":[
				{
					"name":"samples",
					"link":187,
					"label":"samples",
					"type":"LATENT",
					"localized_name":"samples"
				},
				{
					"name":"vae",
					"link":189,
					"label":"vae",
					"type":"VAE",
					"localized_name":"vae"
				}
			],
			"flags":{
				"collapsed":true
			},
			"id":164,
			"type":"VAEDecode",
			"properties":{
				"cnr_id":"comfy-core",
				"ver":"0.3.32",
				"Node name for S&R":"VAEDecode"
			},
			"order":16
		},
		{
			"mode":0,
			"outputs":[
				{
					"name":"output",
					"links":[
						199
					],
					"label":"output",
					"type":"*",
					"localized_name":"output"
				}
			],
			"size":[
				210,
				26
			],
			"pos":[
				721.4827270507812,
				205.56568908691406
			],
			"widgets_values":[
				
			],
			"inputs":[
				{
					"name":"anything",
					"link":198,
					"label":"anything",
					"type":"*",
					"localized_name":"anything"
				}
			],
			"flags":{
				"collapsed":true
			},
			"id":168,
			"type":"easy cleanGpuUsed",
			"properties":{
				"cnr_id":"comfyui-easy-use",
				"ver":"9292f2286207928cfdade99ad1634103470c0799",
				"Node name for S&R":"easy cleanGpuUsed"
			},
			"order":17
		},
		{
			"mode":0,
			"outputs":[
				
			],
			"size":[
				853.2590942382812,
				555.3336791992188
			],
			"pos":[
				-346.0196533203125,
				802.67919921875
			],
			"widgets_values":[
				"img",
				""
			],
			"inputs":[
				{
					"name":"images",
					"link":201,
					"label":"images",
					"type":"IMAGE",
					"localized_name":"images"
				}
			],
			"flags":{
				
			},
			"id":171,
			"type":"SaveImage",
			"title":"Save Image Original",
			"properties":{
				"cnr_id":"comfy-core",
				"ver":"0.3.27",
				"Node name for S&R":"SaveImage"
			},
			"order":18
		},
		{
			"outputs":[
				{
					"name":"MODEL",
					"links":[
						180
					],
					"label":"MODEL",
					"type":"MODEL",
					"localized_name":"MODEL"
				}
			],
			"color":"#323",
			"widgets_values":[
				"Mixture of Diffusers",
				768,
				768,
				64,
				4
			],
			"inputs":[
				{
					"name":"model",
					"link":203,
					"label":"model",
					"type":"MODEL",
					"localized_name":"model"
				}
			],
			"flags":{
				
			},
			"type":"TiledDiffusion",
			"mode":2,
			"bgcolor":"#535",
			"size":[
				315,
				154
			],
			"pos":[
				554.995849609375,
				877.4188842773438
			],
			"id":154,
			"properties":{
				"cnr_id":"ComfyUI-TiledDiffusion",
				"ver":"a155b1bac39147381aeaa52b9be42e545626a44f",
				"Node name for S&R":"TiledDiffusion"
			},
			"order":13
		},
		{
			"outputs":[
				
			],
			"color":"#323",
			"widgets_values":[
				"🔧 Tiled Diffusion – Key Parameters\n\n| Parameter         | Description                                                                 |\n|-------------------|-----------------------------------------------------------------------------|\n| `tile_size`       | Width & height of each tile. Recommended: 512, 768, 1024.                   |\n|                   | 🔹 512 – safest, low VRAM                                                    |\n|                   | 🔹 768 – fast, stable, great for portraits                                   |\n|                   | 🔹 1024 – high detail, but can add \"extra stuff\" & takes longer              |\n| `tile_overlap`    | Pixels shared between tiles. Prevents seams. Use 32–128 based on tile size. |\n|                   | 🔹 32 for 512 tiles, 64 for 768, 128 for 1024                                |\n| `tile_batch_size` | Tiles processed at once. Higher = faster, but uses more VRAM.               |\n|                   | 🔹 1–2 = safe and clean                                                      |\n|                   | 🔹 4–6 = fast on 24GB GPUs (like RTX 4090)                                   |\n\n💡 Tips:\n- Use **square tiles** (width = height)\n- Match **overlap** to tile size to avoid seams\n- 768 is often the sweet spot for quality + speed\n- 1024 tiles may generate more detail, but also more \"creative noise\"\n"
			],
			"inputs":[
				
			],
			"flags":{
				"collapsed":false
			},
			"type":"MarkdownNote",
			"title":"Tiled Diffusion Info",
			"mode":0,
			"bgcolor":"#535",
			"size":[
				481.96246337890625,
				374.152099609375
			],
			"pos":[
				537.2734985351562,
				1097.6727294921875
			],
			"id":155,
			"properties":{
				
			},
			"order":3
		},
		{
			"outputs":[
				
			],
			"color":"#fff0",
			"inputs":[
				
			],
			"flags":{
				"allow_interaction":true
			},
			"type":"Label (rgthree)",
			"title":"2K Landscape | 2560x1440px | 16:9",
			"mode":0,
			"bgcolor":"#fff0",
			"size":[
				399.4140625,
				25
			],
			"pos":[
				-890.8363647460938,
				180.34910583496094
			],
			"id":185,
			"properties":{
				"padding":0,
				"backgroundColor":"transparent",
				"fontFamily":"Arial",
				"borderRadius":0,
				"textAlign":"center",
				"fontSize":25,
				"fontColor":"#ffffff"
			},
			"order":4
		},
		{
			"outputs":[
				{
					"name":"LATENT",
					"slot_index":0,
					"links":[
						186
					],
					"label":"LATENT",
					"type":"LATENT",
					"localized_name":"LATENT"
				}
			],
			"color":"#323",
			"widgets_values":[
				1344,
				768,
				1
			],
			"inputs":[
				
			],
			"flags":{
				
			},
			"type":"EmptySD3LatentImage",
			"mode":0,
			"bgcolor":"#535",
			"size":[
				276.63275146484375,
				106
			],
			"pos":[
				-139.5982208251953,
				583.8009643554688
			],
			"id":162,
			"properties":{
				"cnr_id":"comfy-core",
				"ver":"0.3.32",
				"Node name for S&R":"EmptySD3LatentImage"
			},
			"order":5
		},
		{
			"outputs":[
				{
					"name":"CONDITIONING",
					"slot_index":0,
					"links":[
						11
					],
					"label":"CONDITIONING",
					"type":"CONDITIONING",
					"localized_name":"CONDITIONING"
				}
			],
			"color":"#232",
			"widgets_values":[
				"Natural close-up portrait of a woman with soft curly purple hair, light frizz and volume, subtle flyaway strands, smiling gently and making eye contact with the camera, captured with a smartphone in casual morning light, slight uneven lighting on face, soft natural shadows, visible skin texture, light freckles, no heavy retouching, wearing a simple T-shirt, shallow depth of field with a slightly blurred background, hint of a cozy indoor setting like a window or curtain in the back, authentic and candid expression, amateur photography style"
			],
			"inputs":[
				{
					"name":"clip",
					"link":24,
					"label":"clip",
					"type":"CLIP",
					"localized_name":"clip"
				}
			],
			"flags":{
				
			},
			"type":"CLIPTextEncode",
			"mode":0,
			"bgcolor":"#353",
			"size":[
				424.4290771484375,
				193.0274658203125
			],
			"pos":[
				-488.9686279296875,
				258.99200439453125
			],
			"id":6,
			"properties":{
				"cnr_id":"comfy-core",
				"ver":"0.3.27",
				"Node name for S&R":"CLIPTextEncode"
			},
			"order":11
		},
		{
			"mode":0,
			"outputs":[
				{
					"name":"VAE",
					"links":[
						141,
						145,
						189
					],
					"label":"VAE",
					"type":"VAE",
					"localized_name":"VAE"
				}
			],
			"size":[
				252.23098754882812,
				58
			],
			"pos":[
				244.64601135253906,
				588.2732543945312
			],
			"widgets_values":[
				"ae.safetensors"
			],
			"inputs":[
				
			],
			"flags":{
				
			},
			"id":27,
			"type":"VAELoader",
			"properties":{
				"cnr_id":"comfy-core",
				"ver":"0.3.27",
				"Node name for S&R":"VAELoader"
			},
			"order":6
		},
		{
			"mode":2,
			"outputs":[
				{
					"name":"LATENT",
					"slot_index":0,
					"links":[
						142
					],
					"label":"LATENT",
					"type":"LATENT",
					"localized_name":"LATENT"
				}
			],
			"size":[
				315,
				262
			],
			"pos":[
				547.7832641601562,
				461.8224182128906
			],
			"widgets_values":[
				438762629139537,
				"randomize",
				20,
				1,
				"dpmpp_2m",
				"karras",
				0.7000000000000002
			],
			"inputs":[
				{
					"name":"model",
					"link":180,
					"label":"model",
					"type":"MODEL",
					"localized_name":"model"
				},
				{
					"name":"positive",
					"link":55,
					"label":"positive",
					"type":"CONDITIONING",
					"localized_name":"positive"
				},
				{
					"name":"negative",
					"link":56,
					"label":"negative",
					"type":"CONDITIONING",
					"localized_name":"negative"
				},
				{
					"name":"latent_image",
					"link":197,
					"label":"latent_image",
					"type":"LATENT",
					"localized_name":"latent_image"
				}
			],
			"flags":{
				
			},
			"id":51,
			"type":"KSampler",
			"properties":{
				"cnr_id":"comfy-core",
				"ver":"0.3.27",
				"Node name for S&R":"KSampler"
			},
			"order":22
		},
		{
			"outputs":[
				
			],
			"color":"#fff0",
			"inputs":[
				
			],
			"flags":{
				"allow_interaction":true
			},
			"type":"Label (rgthree)",
			"title":"Denoise between 0.7-0.95",
			"mode":2,
			"bgcolor":"#fff0",
			"size":[
				243.49609375,
				30
			],
			"pos":[
				584.8746948242188,
				731.0587768554688
			],
			"id":156,
			"properties":{
				"padding":5,
				"backgroundColor":"#2a220e",
				"fontFamily":"Arial",
				"borderRadius":10,
				"textAlign":"left",
				"fontSize":20,
				"fontColor":"#ffffff"
			},
			"order":7
		},
		{
			"mode":0,
			"outputs":[
				{
					"name":"MODEL",
					"links":[
						202,
						203
					],
					"label":"MODEL",
					"type":"MODEL",
					"localized_name":"MODEL"
				}
			],
			"size":[
				351.0797119140625,
				82
			],
			"pos":[
				-893.8199462890625,
				260.70025634765625
			],
			"widgets_values":[
				"fluxmania_V.safetensors",
				"default"
			],
			"inputs":[
				
			],
			"flags":{
				
			},
			"id":176,
			"type":"UNETLoader",
			"properties":{
				"cnr_id":"comfy-core",
				"ver":"0.3.30",
				"Node name for S&R":"UNETLoader"
			},
			"order":8
		},
		{
			"outputs":[
				
			],
			"color":"#fff0",
			"inputs":[
				
			],
			"flags":{
				"allow_interaction":true
			},
			"type":"Label (rgthree)",
			"title":"Fluxmania txt2img with Upscaler",
			"mode":0,
			"bgcolor":"#fff0",
			"size":[
				575.7421875,
				40
			],
			"pos":[
				-892.5089721679688,
				139.6504669189453
			],
			"id":180,
			"properties":{
				"padding":0,
				"backgroundColor":"transparent",
				"fontFamily":"Arial",
				"borderRadius":0,
				"textAlign":"center",
				"fontSize":40,
				"fontColor":"#f8a742"
			},
			"order":9
		},
		{
			"outputs":[
				{
					"name":"OPT_CONNECTION",
					"label":"OPT_CONNECTION",
					"type":"*"
				}
			],
			"color":"#432",
			"inputs":[
				
			],
			"flags":{
				
			},
			"type":"Fast Groups Muter (rgthree)",
			"title":"Enable Upscaler?",
			"mode":0,
			"bgcolor":"#653",
			"size":[
				252.23098754882812,
				58
			],
			"pos":[
				246.2351531982422,
				692.8814697265625
			],
			"id":169,
			"properties":{
				"customSortAlphabet":"",
				"matchColors":"",
				"sort":"position",
				"matchTitle":"",
				"showNav":true,
				"toggleRestriction":"default"
			},
			"order":10
		}
	],
	"extra":{
		"VHS_KeepIntermediate":true,
		"VHS_MetadataImage":true,
		"ue_links":[
			
		],
		"0246.VERSION":[
			0,
			0,
			4
		],
		"VHS_latentpreviewrate":0,
		"frontendVersion":"1.20.7",
		"VHS_latentpreview":false,
		"node_versions":{
			"rgthree-comfy":"5d771b8b56a343c24a26e8cea1f0c87c3d58102f",
			"ComfyUI-GGUF":"8098c7149fa4ff14991eb3347a5585051ceeafbe",
			"comfy-core":"v0.3.10-37-gd055325"
		},
		"ds":{
			"offset":[
				990.8013279656827,
				-45.28046763963175
			],
			"scale":0.7247295000000009
		}
	},
	"groups":[
		{
			"color":"#b58b2a",
			"font_size":24,
			"flags":{
				
			},
			"id":1,
			"title":"Upscale",
			"bounding":[
				537.7832641601562,
				237.46620178222656,
				1184.539794921875,
				812.8981323242188
			]
		}
	],
	"links":[
		[
			11,
			6,
			0,
			11,
			0,
			"CONDITIONING"
		],
		[
			24,
			26,
			0,
			6,
			0,
			"CLIP"
		],
		[
			25,
			26,
			0,
			7,
			0,
			"CLIP"
		],
		[
			55,
			11,
			0,
			51,
			1,
			"CONDITIONING"
		],
		[
			56,
			7,
			0,
			51,
			2,
			"CONDITIONING"
		],
		[
			121,
			101,
			0,
			100,
			0,
			"UPSCALE_MODEL"
		],
		[
			122,
			100,
			0,
			102,
			0,
			"IMAGE"
		],
		[
			139,
			102,
			0,
			110,
			0,
			"IMAGE"
		],
		[
			141,
			27,
			0,
			110,
			1,
			"VAE"
		],
		[
			142,
			51,
			0,
			111,
			0,
			"LATENT"
		],
		[
			145,
			27,
			0,
			111,
			1,
			"VAE"
		],
		[
			180,
			154,
			0,
			51,
			0,
			"MODEL"
		],
		[
			184,
			11,
			0,
			163,
			1,
			"CONDITIONING"
		],
		[
			185,
			7,
			0,
			163,
			2,
			"CONDITIONING"
		],
		[
			186,
			162,
			0,
			163,
			3,
			"LATENT"
		],
		[
			187,
			163,
			0,
			164,
			0,
			"LATENT"
		],
		[
			189,
			27,
			0,
			164,
			1,
			"VAE"
		],
		[
			197,
			110,
			0,
			51,
			3,
			"LATENT"
		],
		[
			198,
			164,
			0,
			168,
			0,
			"*"
		],
		[
			199,
			168,
			0,
			100,
			1,
			"IMAGE"
		],
		[
			201,
			164,
			0,
			171,
			0,
			"IMAGE"
		],
		[
			202,
			176,
			0,
			163,
			0,
			"MODEL"
		],
		[
			203,
			176,
			0,
			154,
			0,
			"MODEL"
		],
		[
			210,
			111,
			0,
			184,
			0,
			"IMAGE"
		],
		[
			211,
			184,
			0,
			170,
			0,
			"IMAGE"
		],
		[
			212,
			184,
			0,
			144,
			0,
			"*"
		]
	],
	"id":"c5beec59-2b88-4f3f-ba35-7640a58a9ba6",
	"config":{
		
	},
	"version":0.4,
	"last_node_id":185,
	"revision":0
}